paseto/__init__.py
paseto/exceptions.py
paseto/helpers.py
paseto/keys/__init__.py
paseto/keys/asymmetric_key.py
paseto/keys/symmetric_key.py
paseto/paserk.py
paseto/paseto.py
paseto/protocols/__init__.py
paseto/protocols/protocol.py
paseto/protocols/v2.py
paseto/protocols/v3.py
paseto/protocols/v4.py
paseto-1.0.1.dist-info/LICENSE
paseto-1.0.1.dist-info/WHEEL
paseto-1.0.1.dist-info/METADATA
paseto-1.0.1.dist-info/RECORD
