Metadata-Version: 2.1
Name: paseto
Version: 1.0.1
Summary: Platform-Agnostic Security Tokens for Python (PASETO)
Home-page: https://github.com/rlittlefield/pypaseto
License: MIT
Keywords: paseto,pypaseto,jwt,token
Author: Ryan Littlefield
Author-email: ryan@ryanlittlefield.com
Requires-Python: >=3.7,<4.0
Classifier: Development Status :: 4 - Beta
Classifier: License :: OSI Approved :: MIT License
Classifier: Programming Language :: Python :: 3
Classifier: Programming Language :: Python :: 3.7
Classifier: Programming Language :: Python :: 3.8
Classifier: Programming Language :: Python :: 3.9
Classifier: Topic :: Security :: Cryptography
Requires-Dist: pendulum (>=2.1.2,<3.0.0)
Requires-Dist: pycryptodomex (>=3.10.1,<4.0.0)
Requires-Dist: pysodium (>=0.7.10,<0.8.0)
Project-URL: Repository, https://github.com/rlittlefield/pypaseto
